gsmp_sdk.cpython-36m-x86_64-linux-gnu.so
gsmp_sdk./libboost_system-mt-da72321c.so.1.53.0
gsmp_sdk./libboost_date_time-mt-3d7d21d8.so.1.53.0
gsmp_sdk./libboost_thread-mt-80251d3d.so.1.53.0
gsmp_sdk./libboost_chrono-mt-598921be.so.1.53.0
gsmp_sdk./libboost_atomic-mt-c860e9ce.so.1.53.0
gsmp_sdk-0.0.2.dist-info/WHEEL
gsmp_sdk-0.0.2.dist-info/RECORD
gsmp_sdk-0.0.2.dist-info/LICENSE
gsmp_sdk-0.0.2.dist-info/top_level.txt
gsmp_sdk-0.0.2.dist-info/METADATA
