Metadata-Version: 2.1
Name: gsmp-sdk
Version: 0.0.2
Summary: python binding for gsmp-sdk
Home-page: UNKNOWN
Author: HuNing-He
Author-email: 957278968@qq.com
License: GNU v3
Keywords: gsmp_sdk python cross-platform c++
Platform: UNKNOWN
Classifier: License :: OSI Approved :: MIT License
Classifier: Programming Language :: C
Classifier: Programming Language :: C++
Classifier: Programming Language :: Python
Classifier: Intended Audience :: Developers
Classifier: Topic :: Scientific/Engineering :: Visualization
Classifier: Typing :: Typed
Requires-Python: >=3.6
License-File: LICENSE
